.gitignore
CODE_OF_CONDUCT.md
COPYING.txt
README.rst
TODO
setup.py
smartmerge/__init__.py
smartmerge/__main__.py
smartmerge.egg-info/PKG-INFO
smartmerge.egg-info/SOURCES.txt
smartmerge.egg-info/dependency_links.txt
smartmerge.egg-info/requires.txt
smartmerge.egg-info/top_level.txt
smartmerge/plugins/__init__.py
smartmerge/plugins/changelog_merge/__init__.py
smartmerge/plugins/changelog_merge/changelog_merge.py
smartmerge/plugins/changelog_merge/tests/__init__.py
smartmerge/plugins/changelog_merge/tests/test_changelog_merge.py
smartmerge/plugins/news_merge/README
smartmerge/plugins/news_merge/__init__.py
smartmerge/plugins/news_merge/news_merge.py
smartmerge/plugins/news_merge/parser.py
smartmerge/plugins/news_merge/tests/__init__.py
smartmerge/plugins/news_merge/tests/test_news_merge.py
smartmerge/plugins/po_merge/README
smartmerge/plugins/po_merge/__init__.py
smartmerge/plugins/po_merge/po_merge.py
smartmerge/plugins/po_merge/tests/__init__.py
smartmerge/plugins/po_merge/tests/test_po_merge.py
smartmerge/tests/__init__.py