Metadata-Version: 1.2
Name: smartmerge
Version: 0.0.1
Summary: Three way merge with domain specific knowledge
Home-page: https://www.breezy-vcs.org/
Maintainer: Breezy Developers
Maintainer-email: team@breezy-vcs.org
License: GNU GPLv2 or later
Platform: UNKNOWN
Classifier: Development Status :: 4 - Beta
Classifier: License :: OSI Approved :: GNU General Public License v2 or later (GPLv2+)
Classifier: Programming Language :: Python :: 3.3
Classifier: Programming Language :: Python :: 3.4
Classifier: Programming Language :: Python :: 3.5
Classifier: Programming Language :: Python :: 3.6
Classifier: Programming Language :: Python :: Implementation :: CPython
Classifier: Programming Language :: Python :: Implementation :: PyPy
Classifier: Operating System :: POSIX
